abm1559/__init__.py
abm1559/chain.py
abm1559/simulator.py
abm1559/txpool.py
abm1559/txs.py
abm1559/users.py
abm1559/utils.py
abm1559-0.0.2.dist-info/LICENSE
abm1559-0.0.2.dist-info/METADATA
abm1559-0.0.2.dist-info/WHEEL
abm1559-0.0.2.dist-info/top_level.txt
abm1559-0.0.2.dist-info/RECORD
